{
    "dapp_name": "MoonCatRescue",
    "total_func": 46,
    "analyzed_func": 5,
    "block_num": 18723926,
    "address": "0xc3f733ca98E0daD0386979Eb96fb1722A1A05E69",
    "platform": "ETH",
    "reward": {
        "warning": false,
        "ui": {}
    },
    "fee": {
        "warning": false,
        "modifiable": false,
        "rate": [],
        "ui": {
            "has_fee": false,
            "fee_values": [],
            "fees": {}
        }
    },
    "supply": {
        "amount": [
            19773
        ],
        "unlimited": false,
        "ui": []
    },
    "lock": {
        "backend": false,
        "ui": []
    },
    "clear": {
        "warning": false,
        "ui": false
    },
    "pause": {
        "backend": true,
        "ui": false
    },
    "metadata": {
        "backend": "http",
        "ui": false
    },
    "inconsistency": {
        "reward": false,
        "fee": false,
        "supply": false,
        "lock": false,
        "clear": false,
        "pause": true,
        "metadata": true
    }
}