{
    "dapp_name": "The n project",
    "total_func": 29,
    "analyzed_func": 4,
    "block_num": 18640823,
    "address": "0x05a46f1E545526FB803FF974C790aCeA34D1f2D6",
    "platform": "ETH",
    "reward": {
        "warning": false
    },
    "fee": {
        "warning": false,
        "modifiable": false
    },
    "supply": {
        "amount": [
            8888
        ],
        "unlimited": true
    },
    "lock": false,
    "clear": {
        "warning": false
    },
    "pause": false,
    "metadata": "base64"
}