{
    "dapp_name": "Pandora Digital",
    "total_func": 29,
    "analyzed_func": 4,
    "block_num": 34127431,
    "address": "0x1e28726b27f2a78a380668a6cd653efd8878456c",
    "platform": "BSC",
    "reward": {
        "warning": false
    },
    "fee": {
        "warning": false,
        "modifiable": false,
        "rate": []
    },
    "supply": {
        "amount": [
            28874903341866847833
        ],
        "unlimited": false
    },
    "lock": false,
    "clear": {
        "warning": false
    },
    "pause": false,
    "metadata": ""
}