{
    "dapp_name": "Interport Finance",
    "total_func": 18,
    "analyzed_func": 3,
    "block_num": 18651388,
    "address": "0x2b1D36f5B61AdDAf7DA7ebbd11B35FD8cfb0DE31",
    "platform": "ETH",
    "reward": {
        "warning": false
    },
    "fee": {
        "warning": false,
        "modifiable": false
    },
    "supply": {
        "amount": [
            150000000000000000000000000
        ],
        "unlimited": true
    },
    "lock": false,
    "clear": {
        "warning": false
    },
    "pause": false,
    "metadata": ""
}