{
    "dapp_name": "DDDX Protocol",
    "total_func": 46,
    "analyzed_func": 4,
    "block_num": 33805884,
    "address": "0x322Ba943c19f9ec1EF8ceAD8260b30E789Ca1846",
    "platform": "BSC",
    "reward": {
        "warning": false
    },
    "fee": {
        "warning": true,
        "modifiable": false,
        "0x89afcb44": {
            "0x232b0x227b": [
                [
                    "0xbb4cdb9cbd36b01bd1cbaebf2de08d9173bc095c",
                    "bvudiv_i(Ia_store-some_var_7-*mem_mem_64, Ia_store-2-)"
                ],
                [
                    "0xe9e7cea3dedca5984780bafc599bd69add087d56",
                    "bvudiv_i(Ia_store-some_var_7-*mem_mem_64, Ia_store-2-)"
                ]
            ]
        },
        "0xbc25cf77": {
            "0x232b0x6f6": [
                [
                    "0xbb4cdb9cbd36b01bd1cbaebf2de08d9173bc095c",
                    "mem_mem_64 +\n115792089237316195423570985008687907853269984665640564039457584007913129639935*\nIa_store-8-"
                ]
            ],
            "0x232b0x1bf9S0x1c49": [
                [
                    "0xe9e7cea3dedca5984780bafc599bd69add087d56",
                    "mem_mem_64 +\n115792089237316195423570985008687907853269984665640564039457584007913129639935*\nIa_store-9-"
                ]
            ]
        }
    },
    "supply": {
        "amount": [
            2824489979346923256
        ],
        "unlimited": false
    },
    "lock": false,
    "clear": {
        "warning": false
    },
    "pause": false,
    "metadata": ""
}