{
    "dapp_name": "PoolTogether",
    "total_func": 19,
    "analyzed_func": 0,
    "block_num": 18730989,
    "address": "0x3A06B40C67515cda47E44b57116488F73A441F72",
    "platform": "ETH",
    "reward": {
        "warning": false
    },
    "fee": {
        "warning": false,
        "modifiable": false,
        "rate": []
    },
    "supply": {
        "amount": [],
        "unlimited": false
    },
    "lock": false,
    "clear": {
        "warning": false
    },
    "pause": false,
    "metadata": ""
}