{
    "dapp_name": "Tranche Finance",
    "total_func": 6,
    "analyzed_func": 0,
    "block_num": 18735695,
    "address": "0x5CE49F584257606426498bfd16d770C50bB20254",
    "platform": "ETH",
    "reward": {
        "warning": false
    },
    "fee": {
        "warning": false,
        "modifiable": false,
        "rate": []
    },
    "supply": {
        "amount": [],
        "unlimited": false
    },
    "lock": false,
    "clear": {
        "warning": false
    },
    "pause": false,
    "metadata": ""
}