{
    "dapp_name": "Crypto.com DeFi Swap",
    "total_func": 28,
    "analyzed_func": 4,
    "block_num": 18649164,
    "address": "0x60A26d69263eF43e9a68964bA141263F19D71D51",
    "platform": "ETH",
    "reward": {
        "warning": false
    },
    "fee": {
        "warning": false,
        "modifiable": false
    },
    "supply": {
        "amount": [
            1342046356653141720186
        ],
        "unlimited": false
    },
    "lock": false,
    "clear": {
        "warning": false
    },
    "pause": false,
    "metadata": ""
}