{
    "dapp_name": "Badger.Finance",
    "total_func": 31,
    "analyzed_func": 2,
    "block_num": 18725561,
    "address": "0x6354E79F21B56C11f48bcD7c451BE456D7102A36",
    "platform": "ETH",
    "reward": {
        "warning": false
    },
    "fee": {
        "warning": false,
        "modifiable": false,
        "rate": []
    },
    "supply": {
        "amount": [],
        "unlimited": false
    },
    "lock": false,
    "clear": {
        "warning": false
    },
    "pause": false,
    "metadata": ""
}