{
    "dapp_name": "Tiny World",
    "total_func": 6,
    "analyzed_func": 0,
    "block_num": 34107387,
    "address": "0x72919FD7359461Ea7423bD5c44e3B05B60d919F9",
    "platform": "BSC",
    "reward": {
        "warning": false
    },
    "fee": {
        "warning": false,
        "modifiable": false,
        "rate": []
    },
    "supply": {
        "amount": [],
        "unlimited": false
    },
    "lock": false,
    "clear": {
        "warning": false
    },
    "pause": false,
    "metadata": ""
}