{
    "dapp_name": "AmpleSwap",
    "total_func": 28,
    "analyzed_func": 4,
    "block_num": 33780123,
    "address": "0x74e171d4abae1fbd6fed15fecf6eb2447510b605",
    "platform": "BSC",
    "reward": {
        "warning": false
    },
    "fee": {
        "warning": false,
        "modifiable": false
    },
    "supply": {
        "amount": [
            56370215236902215828
        ],
        "unlimited": false
    },
    "lock": false,
    "clear": {
        "warning": false
    },
    "pause": false,
    "metadata": ""
}