{
    "dapp_name": "Capital DAO Protocol",
    "total_func": 10,
    "analyzed_func": 1,
    "block_num": 18661768,
    "address": "0xA1aC4b6F6e2579c3cbA05C4b1907381c5e7F25a9",
    "platform": "ETH",
    "reward": {
        "warning": false
    },
    "fee": {
        "warning": false,
        "modifiable": false
    },
    "supply": {
        "amount": [],
        "unlimited": false
    },
    "lock": false,
    "clear": {
        "warning": false
    },
    "pause": false,
    "metadata": ""
}