{
    "dapp_name": "HyperDragons",
    "total_func": 10,
    "analyzed_func": 0,
    "block_num": 18735459,
    "address": "0xb0970f61b66f86f2169b4eb3d97da065327633e9",
    "platform": "ETH",
    "reward": {
        "warning": false
    },
    "fee": {
        "warning": false,
        "modifiable": false,
        "rate": []
    },
    "supply": {
        "amount": [],
        "unlimited": false
    },
    "lock": false,
    "clear": {
        "warning": false
    },
    "pause": false,
    "metadata": ""
}