{
    "dapp_name": "Unifi Protocol",
    "total_func": 31,
    "analyzed_func": 4,
    "block_num": 18658249,
    "address": "0xB7985A9bE50C4613b206b96A7Dad043891f73D6E",
    "platform": "ETH",
    "reward": {
        "warning": false
    },
    "fee": {
        "warning": false,
        "modifiable": false
    },
    "supply": {
        "amount": [
            1000
        ],
        "unlimited": false
    },
    "lock": false,
    "clear": {
        "warning": false
    },
    "pause": false,
    "metadata": ""
}