{
    "dapp_name": "Planet IX",
    "total_func": 6,
    "analyzed_func": 0,
    "block_num": 50795982,
    "address": "0xb9d70840cca6e6f71d3c884060ee123e13b4c27d",
    "platform": "Polygon",
    "reward": {
        "warning": false
    },
    "fee": {
        "warning": false,
        "modifiable": false,
        "rate": []
    },
    "supply": {
        "amount": [],
        "unlimited": false
    },
    "lock": false,
    "clear": {
        "warning": false
    },
    "pause": false,
    "metadata": ""
}