{
    "dapp_name": "Planet IX",
    "total_func": 6,
    "analyzed_func": 0,
    "block_num": 50795987,
    "address": "0xbb93395df76d2f8e4ace48e5defab43da18878aa",
    "platform": "Polygon",
    "reward": {
        "warning": false
    },
    "fee": {
        "warning": false,
        "modifiable": false,
        "rate": []
    },
    "supply": {
        "amount": [],
        "unlimited": false
    },
    "lock": false,
    "clear": {
        "warning": false
    },
    "pause": false,
    "metadata": ""
}