{
    "dapp_name": "Planet",
    "total_func": 67,
    "analyzed_func": 0,
    "block_num": 34129263,
    "address": "0xCD221e1504442671671D3330CB8E916a5EDc3FC7",
    "platform": "BSC",
    "reward": {
        "warning": false
    },
    "fee": {
        "warning": false,
        "modifiable": false,
        "rate": []
    },
    "supply": {
        "amount": [
            243087338228538690
        ],
        "unlimited": false
    },
    "lock": false,
    "clear": {
        "warning": false
    },
    "pause": false,
    "metadata": ""
}