{
    "dapp_name": "Foodcourt Finance",
    "total_func": 28,
    "analyzed_func": 4,
    "block_num": 34120960,
    "address": "0xd4ab4530F6d86605727591485812eBc258cd106d",
    "platform": "BSC",
    "reward": {
        "warning": false
    },
    "fee": {
        "warning": false,
        "modifiable": false,
        "rate": []
    },
    "supply": {
        "amount": [
            3442914798495915968217
        ],
        "unlimited": false
    },
    "lock": false,
    "clear": {
        "warning": false
    },
    "pause": false,
    "metadata": ""
}