{
    "dapp_name": "Ether Legends",
    "total_func": 29,
    "analyzed_func": 2,
    "block_num": 18736281,
    "address": "0xe07919263b3b209f4ce065670be4e75e9a1adac3",
    "platform": "ETH",
    "reward": {
        "warning": false
    },
    "fee": {
        "warning": false,
        "modifiable": false,
        "rate": []
    },
    "supply": {
        "amount": [
            99
        ],
        "unlimited": true
    },
    "lock": false,
    "clear": {
        "warning": false
    },
    "pause": false,
    "metadata": "http"
}