{
    "dapp_name": "SwapBased",
    "total_func": 28,
    "analyzed_func": 4,
    "block_num": 7117858,
    "address": "0xe732Ca0f34703eaF823Ff63c30E25E5aEeb61533",
    "platform": "Base",
    "reward": {
        "warning": false
    },
    "fee": {
        "warning": false,
        "modifiable": false
    },
    "supply": {
        "amount": [
            1000000000000000000
        ],
        "unlimited": false
    },
    "lock": false,
    "clear": {
        "warning": false
    },
    "pause": false,
    "metadata": ""
}