{
    "dapp_name": "Milady Maker",
    "total_func": 36,
    "analyzed_func": 5,
    "block_num": 18660406,
    "address": "0x5Af0D9827E0c53E4799BB226655A1de152A425a5",
    "platform": "ETH",
    "reward": {
        "warning": false,
        "ui": {}
    },
    "fee": {
        "warning": false,
        "modifiable": false,
        "ui": {
            "has_fee": false,
            "fee_values": [],
            "fees": {}
        }
    },
    "supply": {
        "amount": [
            10000
        ],
        "unlimited": false,
        "ui": []
    },
    "lock": {
        "backend": false,
        "ui": []
    },
    "clear": {
        "warning": true,
        "0x3ccfd60b": {
            "0xfa4S0x4e6": [
                [
                    "Is",
                    "IH_b"
                ]
            ]
        },
        "ui": false
    },
    "pause": {
        "backend": false,
        "ui": false
    },
    "metadata": {
        "backend": "http",
        "ui": false
    },
    "inconsistency": {
        "reward": false,
        "fee": false,
        "supply": false,
        "lock": false,
        "clear": true,
        "pause": false,
        "metadata": true
    }
}