{
    "dapp_name": "Project Godjira Gen 2",
    "total_func": 25,
    "analyzed_func": 0,
    "block_num": 18724335,
    "address": "0xedc3ad89f7b0963fe23d714b34185713706b815b",
    "platform": "ETH",
    "reward": {
        "warning": false,
        "ui": {}
    },
    "fee": {
        "warning": false,
        "modifiable": false,
        "rate": [],
        "ui": {
            "has_fee": false,
            "fee_values": [],
            "fees": {}
        }
    },
    "supply": {
        "amount": [
            3333,
            0
        ],
        "unlimited": false,
        "ui": [
            30000
        ]
    },
    "lock": {
        "backend": false,
        "ui": []
    },
    "clear": {
        "warning": false,
        "ui": false
    },
    "pause": {
        "backend": false,
        "ui": false
    },
    "metadata": {
        "backend": "http",
        "ui": false
    },
    "inconsistency": {
        "reward": false,
        "fee": false,
        "supply": false,
        "lock": false,
        "clear": false,
        "pause": false,
        "metadata": true
    }
}