{
    "transfer": {},
    "tax": {
        "modifiable": false,
        "0x868ff4a2": {
            "0x17b4S0x633": [
                "Concat(0, Extract(159, 0, Ia_store-7-))",
                "Iv"
            ]
        },
        "0xd0f2a114": {
            "0x2566S0x8c4": [
                "Concat(0, Extract(159, 0, Ia_store-7-))",
                "Iv"
            ]
        },
        "0xc1f26123": {
            "0x2186S0x86b": [
                "Concat(0, Extract(159, 0, Ia_store-7-))",
                "Iv"
            ]
        }
    },
    "mint": {
        "amount": [
            10000
        ],
        "unlimited": false
    },
    "lock": false,
    "clear": {},
    "pause": false,
    "metadata": "ipfs"
}