{
    "1": {
        "clear": false
    },
    "2": {
        "clear": false
    },
    "3": {
        "clear": false
    },
    "4": {
        "clear": false
    },
    "5": {
        "clear": false
    },
    "6": {
        "clear": false
    },
    "7": {
        "clear": false
    },
    "8": {
        "clear": false
    },
    "9": {
        "lock": [
            "5 years"
        ]
    },
    "10": {},
    "11": {
        "lock": [
            "1 year",
            "1 year",
            "30 days",
            "30 days",
            "9 months",
            "9 months"
        ]
    },
    "12": {
        "reward": {}
    },
    "13": {
        "reward": {
            "roi": 0.02
        }
    },
    "14": {
        "reward": {
            "roi": 0.08
        }
    },
    "15": {
        "reward": {
            "roi": 0.1
        }
    },
    "16": {
        "reward": {
            "roi": 0.08
        }
    },
    "17": {
        "reward": {
            "referral": 0.1,
            "roi": 0.03
        }
    },
    "18": {
        "reward": {
            "roi": 0.03
        }
    },
    "19": {
        "reward": {
            "profit": 0.03
        }
    },
    "20": {
        "reward": {
            "roi": 0.03
        }
    },
    "21": {
        "reward": {
            "roi": 0.03
        }
    },
    "22": {
        "reward": {
            "roi": 0.01
        }
    },
    "23": {
        "reward": {
            "roi": 0.08
        }
    },
    "24": {
        "reward": {
            "reward": 0.03,
            "roi": 0.03
        }
    },
    "25": {
        "reward": {
            "roi": 0.08
        }
    },
    "26": {
        "reward": {
            "roi": 0.08
        }
    },
    "27": {
        "reward": {}
    },
    "28": {
        "reward": {}
    },
    "29": {
        "reward": {
            "roi": 0.02,
            "referral": 0.3
        }
    },
    "30": {
        "reward": {
            "roi": 0.1,
            "referral": 0.09
        }
    },
    "31": {
        "reward": {
            "roi": 0.08
        }
    },
    "32": {
        "reward": {
            "return": 0.08,
            "roi": 0.08
        }
    },
    "33": {
        "reward": {
            "roi": 0.4
        }
    },
    "34": {
        "reward": {
            "roi": 0.03
        }
    },
    "35": {
        "reward": {
            "roi": 0.9,
            "referral": 0.1
        }
    },
    "36": {
        "reward": {}
    },
    "37": {
        "reward": {
            "roi": 0.06
        }
    },
    "38": {
        "reward": {
            "roi": 0.02
        }
    },
    "39": {
        "reward": {
            "roi": 0.015
        }
    },
    "40": {
        "reward": {
            "roi": 0.16
        }
    },
    "41": {
        "reward": {
            "roi": 0.08
        }
    },
    "42": {
        "supply": 250000000
    },
    "43": {
        "supply": 275000000
    },
    "44": {
        "supply": 8000000
    },
    "45": {
        "supply": 50000000
    },
    "46": {
        "supply": 21000000
    },
    "47": {
        "supply": 3000000000
    },
    "48": {
        "supply": 500000000
    },
    "49": {
        "metadata": false
    },
    "50": {
        "pause": false
    },
    "51": {
        "pause": false
    },
    "52": {
        "pause": false
    },
    "53": {
        "pause": false
    },
    "54": {
        "fee": {
            "has_fee": false,
            "fee_values": [],
            "fees": {}
        }
    },
    "55": {
        "fee": {
            "has_fee": false,
            "fee_values": [],
            "fees": {}
        }
    },
    "56": {
        "fee": {
            "has_fee": false,
            "fee_values": [],
            "fees": {}
        }
    },
    "57": {
        "fee": {
            "has_fee": true,
            "fee_values": [
                0.16,
                0.05
            ],
            "fees": {
                "trade": 0.05
            }
        }
    },
    "58": {
        "fee": {
            "has_fee": false,
            "fee_values": [],
            "fees": {}
        }
    },
    "59": {
        "fee": {
            "has_fee": true,
            "fee_values": [
                0.01,
                0.01
            ],
            "fees": {
                "sell": 0.01,
                "dev": 0.01
            }
        }
    },
    "60": {
        "fee": {
            "has_fee": true,
            "fee_values": [
                0.04,
                0.15,
                0.04,
                0.07
            ],
            "fees": {
                "trade": 0.15,
                "dev": 0.04
            }
        }
    },
    "61": {
        "fee": {
            "has_fee": true,
            "fee_values": [
                0.1
            ],
            "fees": {}
        }
    },
    "62": {
        "fee": {
            "has_fee": true,
            "fee_values": [
                0.1
            ],
            "fees": {}
        }
    },
    "63": {
        "fee": {
            "has_fee": false,
            "fee_values": [],
            "fees": {}
        }
    },
    "64": {
        "fee": {
            "has_fee": false,
            "fee_values": [],
            "fees": {}
        }
    },
    "65": {
        "fee": {
            "has_fee": true,
            "fee_values": [
                0.06,
                0.14
            ],
            "fees": {
                "withdrawal": 0.06,
                "deposit": 0.14
            }
        }
    },
    "66": {
        "fee": {
            "has_fee": true,
            "fee_values": [
                0.09,
                0.02,
                0.02,
                0.02,
                0.02,
                0.03,
                0.03,
                0.09,
                0.02
            ],
            "fees": {}
        }
    },
    "67": {
        "fee": {
            "has_fee": false,
            "fee_values": [],
            "fees": {}
        }
    },
    "68": {
        "fee": {
            "has_fee": false,
            "fee_values": [],
            "fees": {}
        }
    },
    "69": {
        "fee": {
            "has_fee": false,
            "fee_values": [],
            "fees": {}
        }
    },
    "70": {
        "fee": {
            "has_fee": true,
            "fee_values": [
                0.8
            ],
            "fees": {}
        }
    },
    "71": {
        "fee": {
            "has_fee": true,
            "fee_values": [
                0.003
            ],
            "fees": {
                "trade": 0.00025
            }
        }
    },
    "72": {
        "fee": {
            "has_fee": true,
            "fee_values": [
                0.1,
                0.09,
                0.1,
                0.1,
                0.09
            ],
            "fees": {
                "buy": 0.09
            }
        }
    },
    "73": {
        "fee": {
            "has_fee": true,
            "fee_values": [
                0.5
            ],
            "fees": {}
        }
    },
    "74": {
        "fee": {
            "has_fee": false,
            "fee_values": [],
            "fees": {}
        }
    },
    "75": {
        "fee": {
            "has_fee": false,
            "fee_values": [],
            "fees": {}
        }
    },
    "76": {
        "fee": {
            "has_fee": true,
            "fee_values": [
                0.04
            ],
            "fees": {}
        }
    },
    "77": {
        "fee": {
            "has_fee": true,
            "fee_values": [
                0.01,
                0.1
            ],
            "fees": {
                "buy": 0.01,
                "sell": 0.1
            }
        }
    },
    "78": {
        "fee": {
            "has_fee": false,
            "fee_values": [],
            "fees": {}
        }
    },
    "79": {
        "fee": {
            "has_fee": true,
            "fee_values": [
                0.15,
                0.15,
                0.015,
                0.015
            ],
            "fees": {
                "buy": 0.15,
                "sell": 0.15
            }
        }
    },
    "80": {
        "fee": {
            "has_fee": true,
            "fee_values": [
                0.8,
                0.8
            ],
            "fees": {}
        }
    },
    "81": {
        "fee": {
            "has_fee": true,
            "fee_values": [
                0.09,
                0.09,
                0.09,
                0.09,
                0.09,
                0.09,
                0.09
            ],
            "fees": {
                "liquidity": 0.09
            }
        }
    },
    "82": {
        "fee": {
            "has_fee": false,
            "fee_values": [],
            "fees": {}
        }
    },
    "83": {
        "fee": {
            "has_fee": true,
            "fee_values": [
                0.1,
                0.1,
                0.6
            ],
            "fees": {}
        }
    },
    "84": {
        "fee": {
            "has_fee": true,
            "fee_values": [
                0.1,
                0.1,
                0.13,
                0.03,
                0.03
            ],
            "fees": {
                "sell": 0.03
            }
        }
    },
    "85": {
        "fee": {
            "has_fee": false,
            "fee_values": [],
            "fees": {}
        }
    },
    "86": {
        "fee": {
            "has_fee": false,
            "fee_values": [],
            "fees": {}
        }
    },
    "87": {
        "fee": {
            "has_fee": false,
            "fee_values": [],
            "fees": {}
        }
    },
    "88": {
        "fee": {
            "has_fee": true,
            "fee_values": [
                0.3,
                0.3
            ],
            "fees": {
                "withdrawal": 0.3
            }
        }
    },
    "89": {
        "fee": {
            "has_fee": true,
            "fee_values": [
                0.15
            ],
            "fees": {
                "withdrawal": 0.15
            }
        }
    },
    "90": {
        "fee": {
            "has_fee": false,
            "fee_values": [],
            "fees": {}
        }
    },
    "91": {
        "fee": {
            "has_fee": true,
            "fee_values": [
                0.1
            ],
            "fees": {}
        }
    },
    "92": {
        "fee": {
            "has_fee": false,
            "fee_values": [],
            "fees": {}
        }
    },
    "93": {
        "fee": {
            "has_fee": true,
            "fee_values": [
                0.6,
                0.6
            ],
            "fees": {
                "withdrawal": 0.6
            }
        }
    },
    "94": {
        "fee": {
            "has_fee": true,
            "fee_values": [
                0.03,
                0.03,
                0.02,
                29.2
            ],
            "fees": {
                "dev": 0.02
            }
        }
    }
}